django_business_days-0.2.0.dist-info/dependency_links.txt
django_business_days-0.2.0.dist-info/entry_points.txt
django_business_days-0.2.0.dist-info/METADATA
django_business_days-0.2.0.dist-info/top_level.txt
django_business_days-0.2.0.dist-info/WHEEL
django_business_days/__init__.py
django_business_days/calendar.py
django_business_days/querysets.py
django_business_days/models.py
django_business_days/admin.py
django_business_days/migrations/__init__.py
django_business_days/migrations/0001_initial.py
django_business_days/migrations/0002_auto_20201202_1208.py
django_business_days-0.2.0.dist-info/LICENSE
django_business_days-0.2.0.dist-info/AUTHORS
django_business_days-0.2.0.dist-info/RECORD