Metadata-Version: 2.1
Name: django-business-days
Version: 0.2.0
Summary: Wrapper around business-python to control days in django
Project-URL: Repository, https://gitlab.com/cyberbudy/django-business-days
Author: Alex Uzjakov
Author-email: cyberbudy@gmail.com
License: MIT
Requires-Python: >=3.6
Classifier: Development Status :: 4 - Beta
Classifier: Programming Language :: Python :: 3
Classifier: Framework :: Django
Classifier: Intended Audience :: Developers
Classifier: Topic :: Utilities
Classifier: License :: OSI Approved :: MIT License
Classifier: Operating System :: OS Independent
Requires-Dist: business-python==1.*,>=1.0.3
Requires-Dist: django>=3.0.0
